monkt/__init__.py
monkt/core.py
monkt-0.1.0.dist-info/METADATA
monkt-0.1.0.dist-info/WHEEL
monkt-0.1.0.dist-info/top_level.txt
monkt-0.1.0.dist-info/RECORD
