Metadata-Version: 2.1
Name: monkt
Version: 0.1.0
Summary: Transform Documents into AI-Ready Markdown or structured JSON
Author-email: Simeon Emanuilov <simeon@monkt.com>
Project-URL: Homepage, https://monkt.com
Project-URL: Bug Tracker, https://github.com/yourusername/monkt/issues
Classifier: Programming Language :: Python :: 3
Classifier: License :: OSI Approved :: MIT License
Classifier: Operating System :: OS Independent
Requires-Python: >=3.7
